keras_unet/__init__.py
keras_unet/losses.py
keras_unet/metrics.py
keras_unet/metrics_np.py
keras_unet/utils.py
keras_unet/models/__init__.py
keras_unet/models/custom_unet.py
keras_unet/models/custom_vnet.py
keras_unet/models/satellite_unet.py
keras_unet/models/vanilla_unet.py
keras_unet-0.1.2.dist-info/LICENSE
keras_unet-0.1.2.dist-info/METADATA
keras_unet-0.1.2.dist-info/WHEEL
keras_unet-0.1.2.dist-info/top_level.txt
keras_unet-0.1.2.dist-info/RECORD
